mongotime/__init__.py
mongotime/app.py
mongotime/dumper.py
mongotime/plugins.py
mongotime/reporter.py
mongotime/sampler.py
mongotime/thread_with_stop.py
mongotime/version.py
mongotime-0.1.0.dist-info/DESCRIPTION.rst
mongotime-0.1.0.dist-info/METADATA
mongotime-0.1.0.dist-info/RECORD
mongotime-0.1.0.dist-info/WHEEL
mongotime-0.1.0.dist-info/entry_points.txt
mongotime-0.1.0.dist-info/metadata.json
mongotime-0.1.0.dist-info/top_level.txt
