Metadata-Version: 2.0
Name: mongotime
Version: 0.1.0
Summary: Sampling Profiler for Mongo DB - see what the DB spends time on
Home-page: http://github.com/heewa/mongotime
Author: Heewa Barfchin
Author-email: heewa.b@gmail.com
License: MIT
Download-URL: https://github.com/heewa/mongotime/archive/v0.1.0.tar.gz
Keywords: mongo mongodb database db perf performance profile profiler
Platform: UNKNOWN
Classifier: Development Status :: 3 - Alpha
Classifier: Programming Language :: Python :: 2.7
Classifier: Intended Audience :: Developers
Classifier: Intended Audience :: System Administrators
Classifier: License :: OSI Approved :: MIT License
Classifier: Environment :: Console
Classifier: Topic :: Database
Classifier: Topic :: System
Classifier: Topic :: System :: Benchmark
Classifier: Topic :: System :: Monitoring
Requires-Dist: click (<7,>=6.7)
Requires-Dist: pymongo (<4,>=3.6.0)
